myfunctions_yasinozturk3580/__init__.py
myfunctions_yasinozturk3580/math.py
myfunctions_yasinozturk3580-0.0.15.dist-info/METADATA
myfunctions_yasinozturk3580-0.0.15.dist-info/WHEEL
myfunctions_yasinozturk3580-0.0.15.dist-info/top_level.txt
myfunctions_yasinozturk3580-0.0.15.dist-info/RECORD
