Metadata-Version: 2.1
Name: myfunctions-yasinozturk3580
Version: 0.0.15
Summary: A description of your package
Home-page: http://github.com/yasinozturk3580/
Author: yasin ozturk
Author-email: yasinozturk3580@gmail.com
License: MIT
Platform: UNKNOWN
Classifier: Programming Language :: Python :: 3
Classifier: License :: OSI Approved :: MIT License
Classifier: Operating System :: OS Independent
Requires-Python: >=3.6
